{"version":5,"locale":"ru","dpi":"hdpi","size":125897680,"sizeMB":120.07,"parts":{"count":5,"items":[{"size":26415701,"sizeMB":25.19,"part":1,"checksum":"","path":"/expansions/5-ru-hdpi-Part_1/part1.zip"},{"size":22009030,"sizeMB":20.99,"part":2,"checksum":"","path":"/expansions/5-ru-hdpi-Part_1/part2.zip"},{"size":27144764,"sizeMB":25.89,"part":3,"checksum":"","path":"/expansions/5-ru-hdpi-Part_1/part3.zip"},{"size":25418670,"sizeMB":24.24,"part":4,"checksum":"","path":"/expansions/5-ru-hdpi-Part_1/part4.zip"},{"size":24909515,"sizeMB":23.76,"part":5,"checksum":"","path":"/expansions/5-ru-hdpi-Part_1/part5.zip"}]}}